odoo9_addon_crm_deduplicate_acl-9.0.1.1.0-py2.7-nspkg.pth
odoo9_addon_crm_deduplicate_acl-9.0.1.1.0.dist-info/top_level.txt
odoo9_addon_crm_deduplicate_acl-9.0.1.1.0.dist-info/WHEEL
odoo9_addon_crm_deduplicate_acl-9.0.1.1.0.dist-info/RECORD
odoo9_addon_crm_deduplicate_acl-9.0.1.1.0.dist-info/metadata.json
odoo9_addon_crm_deduplicate_acl-9.0.1.1.0.dist-info/DESCRIPTION.rst
odoo9_addon_crm_deduplicate_acl-9.0.1.1.0.dist-info/METADATA
odoo9_addon_crm_deduplicate_acl-9.0.1.1.0.dist-info/namespace_packages.txt
odoo_addons/crm_deduplicate_acl/__openerp__.py
odoo_addons/crm_deduplicate_acl/__init__.py
odoo_addons/crm_deduplicate_acl/README.rst
odoo_addons/crm_deduplicate_acl/security/crm_deduplicate_acl_security.xml
odoo_addons/crm_deduplicate_acl/i18n/it.po
odoo_addons/crm_deduplicate_acl/i18n/es.po
odoo_addons/crm_deduplicate_acl/i18n/tr.po
odoo_addons/crm_deduplicate_acl/i18n/hr.po
odoo_addons/crm_deduplicate_acl/i18n/sl.po
odoo_addons/crm_deduplicate_acl/i18n/de.po
odoo_addons/crm_deduplicate_acl/i18n/pt_BR.po
odoo_addons/crm_deduplicate_acl/i18n/sk.po
odoo_addons/crm_deduplicate_acl/views/base_partner_merge_view.xml
odoo_addons/crm_deduplicate_acl/wizards/partner_merge.py
odoo_addons/crm_deduplicate_acl/wizards/__init__.py
odoo_addons/crm_deduplicate_acl/wizards/partner_merge_view.xml
odoo_addons/crm_deduplicate_acl/images/perms.png
odoo_addons/crm_deduplicate_acl/static/description/icon.svg
odoo_addons/crm_deduplicate_acl/static/description/icon.png
